agent_threads/__init__.py
agent_threads/db/conn.py
agent_threads/db/models.py
agent_threads/thread.py
agent_threads-0.1.2.dist-info/LICENSE
agent_threads-0.1.2.dist-info/METADATA
agent_threads-0.1.2.dist-info/WHEEL
agent_threads-0.1.2.dist-info/RECORD
